b2binpay/__init__.py
b2binpay/client.py
b2binpay/exeptions.py
b2binpay_python-0.0.4.dist-info/METADATA
b2binpay_python-0.0.4.dist-info/WHEEL
b2binpay_python-0.0.4.dist-info/top_level.txt
b2binpay_python-0.0.4.dist-info/RECORD
